watcherclient/__init__.py
watcherclient/_i18n.py
watcherclient/client.py
watcherclient/exceptions.py
watcherclient/shell.py
watcherclient/version.py
watcherclient/common/__init__.py
watcherclient/common/api_versioning.py
watcherclient/common/base.py
watcherclient/common/command.py
watcherclient/common/httpclient.py
watcherclient/common/utils.py
watcherclient/common/apiclient/__init__.py
watcherclient/common/apiclient/base.py
watcherclient/common/apiclient/exceptions.py
watcherclient/locale/watcherclient.pot
watcherclient/locale/fr/LC_MESSAGES/watcherclient.po
watcherclient/osc/__init__.py
watcherclient/osc/plugin.py
watcherclient/tests/__init__.py
watcherclient/tests/client_functional/__init__.py
watcherclient/tests/client_functional/v1/__init__.py
watcherclient/tests/client_functional/v1/base.py
watcherclient/tests/client_functional/v1/test_action.py
watcherclient/tests/client_functional/v1/test_action_plan.py
watcherclient/tests/client_functional/v1/test_audit.py
watcherclient/tests/client_functional/v1/test_audit_template.py
watcherclient/tests/client_functional/v1/test_goal.py
watcherclient/tests/client_functional/v1/test_scoring_engine.py
watcherclient/tests/client_functional/v1/test_service.py
watcherclient/tests/client_functional/v1/test_strategy.py
watcherclient/tests/unit/__init__.py
watcherclient/tests/unit/keystone_client_fixtures.py
watcherclient/tests/unit/test_client.py
watcherclient/tests/unit/test_import.py
watcherclient/tests/unit/test_utils.py
watcherclient/tests/unit/utils.py
watcherclient/tests/unit/common/__init__.py
watcherclient/tests/unit/common/test_api_versioning.py
watcherclient/tests/unit/v1/__init__.py
watcherclient/tests/unit/v1/base.py
watcherclient/tests/unit/v1/test_action.py
watcherclient/tests/unit/v1/test_action_plan.py
watcherclient/tests/unit/v1/test_action_plan_shell.py
watcherclient/tests/unit/v1/test_action_shell.py
watcherclient/tests/unit/v1/test_audit.py
watcherclient/tests/unit/v1/test_audit_shell.py
python_watcherclient-4.9.0.dist-info/AUTHORS
python_watcherclient-4.9.0.dist-info/LICENSE
python_watcherclient-4.9.0.dist-info/METADATA
python_watcherclient-4.9.0.dist-info/WHEEL
python_watcherclient-4.9.0.dist-info/entry_points.txt
python_watcherclient-4.9.0.dist-info/pbr.json
python_watcherclient-4.9.0.dist-info/top_level.txt
python_watcherclient-4.9.0.dist-info/RECORD
