Metadata-Version: 2.1
Name: python-watcherclient
Version: 4.9.0
Summary: Python client library for Watcher API
Home-page: https://docs.openstack.org/python-watcherclient/latest/
Author: OpenStack
Author-email: openstack-discuss@lists.openstack.org
Classifier: Environment :: OpenStack
Classifier: Intended Audience :: Information Technology
Classifier: Intended Audience :: System Administrators
Classifier: License :: OSI Approved :: Apache Software License
Classifier: Operating System :: POSIX :: Linux
Classifier: Programming Language :: Python
Classifier: Programming Language :: Python :: 3
Classifier: Programming Language :: Python :: 3.10
Classifier: Programming Language :: Python :: 3.11
Classifier: Programming Language :: Python :: 3.12
Requires-Python: >=3.10
License-File: LICENSE
License-File: AUTHORS
Requires-Dist: cliff !=2.9.0,>=2.11.0
Requires-Dist: osc-lib >=1.10.0
Requires-Dist: oslo.i18n >=3.20.0
Requires-Dist: oslo.serialization !=2.19.1,>=2.18.0
Requires-Dist: oslo.utils >=3.36.0
Requires-Dist: pbr !=2.1.0,>=3.1.1
Requires-Dist: keystoneauth1 >=3.4.0
Requires-Dist: PyYAML >=3.13
